dj_warning_forms/__init__.py
dj_warning_forms/apps.py
dj_warning_forms/forms.py
dj_warning_forms/static/css/dj_warning_forms.css
dj_warning_forms/static/js/dj_warning_forms.js
dj_warning_forms/templates/dj_warning_forms/base.html
dj_warning_forms-0.1.0.dist-info/AUTHORS.rst
dj_warning_forms-0.1.0.dist-info/LICENSE
dj_warning_forms-0.1.0.dist-info/METADATA
dj_warning_forms-0.1.0.dist-info/WHEEL
dj_warning_forms-0.1.0.dist-info/top_level.txt
dj_warning_forms-0.1.0.dist-info/RECORD
