Metadata-Version: 2.1
Name: dj-warning-forms
Version: 0.1.0
Summary: Add warnings to your Django Forms easily
Home-page: https://github.com/dnmellen/dj-warning-forms
Author: Diego Navarro Mellen
Author-email: dnmellen@gmail.com
License: BSD
Keywords: dj-warning-forms
Platform: UNKNOWN
Classifier: Development Status :: 3 - Alpha
Classifier: Intended Audience :: Developers
Classifier: License :: OSI Approved :: BSD License
Classifier: Natural Language :: English
Classifier: Programming Language :: Python :: 3.10
License-File: LICENSE
License-File: AUTHORS.rst
Requires-Dist: Django (>=3.2)
